hacs_tools/__init__.py
hacs_tools/py.typed
hacs_tools/tools.py
hacs_tools/domains/__init__.py
hacs_tools/domains/admin_operations.py
hacs_tools/domains/ai_integrations.py
hacs_tools/domains/clinical_workflows.py
hacs_tools/domains/descriptions.py
hacs_tools/domains/development_tools.py
hacs_tools/domains/fhir_integration.py
hacs_tools/domains/healthcare_analytics.py
hacs_tools/domains/memory_operations.py
hacs_tools/domains/resource_management.py
hacs_tools/domains/schema_discovery.py
hacs_tools/domains/vector_search.py
hacs_tools-0.4.3.dist-info/METADATA
hacs_tools-0.4.3.dist-info/WHEEL
hacs_tools-0.4.3.dist-info/RECORD
