Metadata-Version: 2.4
Name: hacs-tools
Version: 0.4.3
Summary: Core tools and utilities for HACS (Healthcare Agent Communication Standard)
Project-URL: Homepage, https://github.com/solanovisitor/hacs-ai
Project-URL: Documentation, https://github.com/solanovisitor/hacs-ai/blob/main/docs/
Project-URL: Repository, https://github.com/solanovisitor/hacs-ai
Project-URL: Issues, https://github.com/solanovisitor/hacs-ai/issues
Project-URL: Changelog, https://github.com/solanovisitor/hacs-ai/blob/main/CHANGELOG.md
Author-email: Solano Todeschini <solanovisitor@gmail.com>
Maintainer-email: Solano Todeschini <solanovisitor@gmail.com>
License: MIT
Keywords: crud,evidence,healthcare,memory,search,tools,validation
Classifier: Development Status :: 4 - Beta
Classifier: Intended Audience :: Developers
Classifier: Intended Audience :: Healthcare Industry
Classifier: License :: OSI Approved :: MIT License
Classifier: Operating System :: OS Independent
Classifier: Programming Language :: Python :: 3
Classifier: Programming Language :: Python :: 3.11
Classifier: Programming Language :: Python :: 3.12
Classifier: Topic :: Scientific/Engineering :: Medical Science Apps.
Classifier: Topic :: Software Development :: Libraries :: Python Modules
Classifier: Typing :: Typed
Requires-Python: >=3.11
Requires-Dist: hacs-core>=0.4.3
Requires-Dist: pydantic>=2.11.7
Requires-Dist: requests>=2.32.4
Requires-Dist: typing-extensions>=4.0.0
Provides-Extra: all
Requires-Dist: hacs-persistence>=0.4.3; extra == 'all'
Provides-Extra: clinical
Requires-Dist: hacs-persistence>=0.4.3; extra == 'clinical'
Provides-Extra: dev
Requires-Dist: black>=23.0.0; extra == 'dev'
Requires-Dist: mypy>=1.8.0; extra == 'dev'
Requires-Dist: pytest-asyncio>=0.21.0; extra == 'dev'
Requires-Dist: pytest-cov>=4.0.0; extra == 'dev'
Requires-Dist: pytest>=7.0.0; extra == 'dev'
Requires-Dist: ruff>=0.4.0; extra == 'dev'
